mopidy_gmusic/__init__.py
mopidy_gmusic/backend.py
mopidy_gmusic/commands.py
mopidy_gmusic/ext.conf
mopidy_gmusic/library.py
mopidy_gmusic/playback.py
mopidy_gmusic/playlists.py
mopidy_gmusic/repeating_timer.py
mopidy_gmusic/scrobbler_frontend.py
mopidy_gmusic/session.py
mopidy_gmusic/translator.py
Mopidy_GMusic-4.0.1.dist-info/LICENSE
Mopidy_GMusic-4.0.1.dist-info/METADATA
Mopidy_GMusic-4.0.1.dist-info/WHEEL
Mopidy_GMusic-4.0.1.dist-info/entry_points.txt
Mopidy_GMusic-4.0.1.dist-info/top_level.txt
Mopidy_GMusic-4.0.1.dist-info/RECORD
